PyAAVF/__init__.py
PyAAVF/model.py
PyAAVF/parser.py
PyAAVF/utils.py
PyAAVF/test/__init__.py
PyAAVF/test/test_parser.py
PyAAVF/test/test_utils.py
PyAAVF-0.1.0.dist-info/LICENSE
PyAAVF-0.1.0.dist-info/METADATA
PyAAVF-0.1.0.dist-info/WHEEL
PyAAVF-0.1.0.dist-info/top_level.txt
PyAAVF-0.1.0.dist-info/RECORD
